ailingo/__init__.py
ailingo/cli.py
ailingo/input_source/__init__.py
ailingo/input_source/editor_source.py
ailingo/input_source/file_source.py
ailingo/input_source/url_source.py
ailingo/llm.py
ailingo/output_source/__init__.py
ailingo/output_source/console_source.py
ailingo/output_source/file_source.py
ailingo/prompt.py
ailingo/prompts/rewrite.j2
ailingo/prompts/translate.j2
ailingo/prompts/user.j2
ailingo/translator.py
ailingo/utils.py
ailingo-0.4.0.dist-info/LICENSE
ailingo-0.4.0.dist-info/METADATA
ailingo-0.4.0.dist-info/WHEEL
ailingo-0.4.0.dist-info/entry_points.txt
ailingo-0.4.0.dist-info/RECORD
