Metadata-Version: 2.1
Name: ailingo
Version: 0.4.0
Summary: A CLI Tool for Local File Translation Using Generative AI(LLMs)
License: MIT
Author: Mitsuki Ogasahara
Author-email: negiga@gmail.com
Requires-Python: >=3.11,<4.0
Classifier: License :: OSI Approved :: MIT License
Classifier: Programming Language :: Python :: 3
Classifier: Programming Language :: Python :: 3.11
Classifier: Programming Language :: Python :: 3.12
Provides-Extra: all
Provides-Extra: anthropic-vertex
Provides-Extra: aws
Provides-Extra: google
Requires-Dist: anthropic[vertex] (>=0.28.0,<0.29.0) ; extra == "anthropic-vertex" or extra == "all"
Requires-Dist: boto3 (>=1.28.57) ; extra == "aws" or extra == "all"
Requires-Dist: google-cloud-aiplatform (>=1.52.0,<2.0.0) ; extra == "google" or extra == "all"
Requires-Dist: google-generativeai (>=0.5.4,<0.6.0) ; extra == "google" or extra == "all"
Requires-Dist: instructor (>=1.3.2,<2.0.0)
Requires-Dist: jinja2 (>=3.1.4,<4.0.0)
Requires-Dist: litellm (>=1.38.8,<2.0.0)
Requires-Dist: lxml-html-clean (>=0.1.1,<0.2.0)
Requires-Dist: requests-html (>=0.10.0,<0.11.0)
Requires-Dist: rich (>=13.7.1,<14.0.0)
Requires-Dist: typer (>=0.12.3,<0.13.0)
